[
    {
        "episode": 1,
        "post": "This episode is awesome!",
        "likes": 0
    },

    {
        "episode": 2,
        "post": "This episode is awesome!",
        "likes": 0
    },

    {
        "episode": 3,
        "post": "This episode is awesome!",
        "likes": 0
    },

    {
        "episode": 4,
        "post": "This episode is awesome!",
        "likes": 0
    },

    {
        "episode": 5,
        "post": "This episode is awesome!",
        "likes": 0
    },

    {
        "episode": 6,
        "post": "This episode is awesome!",
        "likes": 0
    },

    {
        "episode": 7,
        "post": "This episode is awesome!",
        "likes": 0
    },

    {
        "episode": 8,
        "post": "This episode is awesome!",
        "likes": 0
    },

    {
        "episode": 9,
        "post": "This episode is awesome!",
        "likes": 0
    },

    {
        "episode": 10,
        "post": "This episode is awesome!",
        "likes": 0
    },

    {
        "episode": 11,
        "post": "This episode is awesome!",
        "likes": 0
    },

    {
        "episode": 12,
        "post": "This episode is awesome!",
        "likes": 0
    },

    {
        "episode": 13,
        "post": "This episode is awesome!",
        "likes": 0
    },

    {
        "episode": 14,
        "post": "This episode is awesome!",
        "likes": 0
    },

    {
        "episode": 15,
        "post": "This episode is awesome!",
        "likes": 0
    },

    {
        "episode": 16,
        "post": "This episode is awesome!",
        "likes": 0
    },

    {
        "episode": 17,
        "post": "This episode is awesome!",
        "likes": 0
    },

    {
        "episode": 18,
        "post": "This episode is awesome!",
        "likes": 0
    },

    {
        "episode": 19,
        "post": "This episode is awesome!",
        "likes": 0
    },

    {
        "episode": 20,
        "post": "This episode is awesome!",
        "likes": 0
    }
]